{
  "_format": "hh-sol-cache-2",
  "files": {
    "/home/hskang9/standard-protocol/contracts/interfaces/IAggregator.sol": {
      "lastModificationDate": 1609690850719,
      "contentHash": "636e09e5f6f72909e19bf9e3fc8d9de6",
      "sourceName": "contracts/interfaces/IAggregator.sol",
      "solcConfig": {
        "version": "0.6.12",
        "settings": {
          "optimizer": {
            "enabled": true,
            "runs": 200
          },
          "outputSelection": {
            "*": {
              "*": [
                "abi",
                "evm.bytecode",
                "evm.deployedBytecode",
                "evm.methodIdentifiers"
              ],
              "": [
                "ast"
              ]
            }
          }
        }
      },
      "imports": [],
      "versionPragmas": [
        "^0.6.0"
      ],
      "artifacts": [
        "IAggregator"
      ]
    },
    "/home/hskang9/standard-protocol/contracts/treasury/exchanges/Exchange.sol": {
      "lastModificationDate": 1609691279138,
      "contentHash": "13c18c8b715f1f8573e1a348348b1262",
      "sourceName": "contracts/treasury/exchanges/Exchange.sol",
      "solcConfig": {
        "version": "0.6.12",
        "settings": {
          "optimizer": {
            "enabled": true,
            "runs": 200
          },
          "outputSelection": {
            "*": {
              "*": [
                "abi",
                "evm.bytecode",
                "evm.deployedBytecode",
                "evm.methodIdentifiers"
              ],
              "": [
                "ast"
              ]
            }
          }
        }
      },
      "imports": [
        "@openzeppelin/contracts/math/Math.sol",
        "@openzeppelin/contracts/math/SafeMath.sol",
        "@openzeppelin/contracts/token/ERC20/IERC20.sol",
        "@openzeppelin/contracts/token/ERC20/SafeERC20.sol",
        "@openzeppelin/contracts/utils/ReentrancyGuard.sol",
        "../../ownership/Operator.sol",
        "../../interfaces/IAggregator.sol",
        "../../utils/ContractGuard.sol"
      ],
      "versionPragmas": [
        "^0.6.0"
      ],
      "artifacts": [
        "Exchange"
      ]
    },
    "/home/hskang9/standard-protocol/node_modules/@openzeppelin/contracts/math/Math.sol": {
      "lastModificationDate": 1609182752075,
      "contentHash": "d9d26ff981b836b0e3bb45940cd56321",
      "sourceName": "@openzeppelin/contracts/math/Math.sol",
      "solcConfig": {
        "version": "0.6.12",
        "settings": {
          "optimizer": {
            "enabled": true,
            "runs": 200
          },
          "outputSelection": {
            "*": {
              "*": [
                "abi",
                "evm.bytecode",
                "evm.deployedBytecode",
                "evm.methodIdentifiers"
              ],
              "": [
                "ast"
              ]
            }
          }
        }
      },
      "imports": [],
      "versionPragmas": [
        "^0.6.0"
      ],
      "artifacts": [
        "Math"
      ]
    },
    "/home/hskang9/standard-protocol/node_modules/@openzeppelin/contracts/math/SafeMath.sol": {
      "lastModificationDate": 1609182752075,
      "contentHash": "168f50d923a8f64094d8e761ca2e5fe6",
      "sourceName": "@openzeppelin/contracts/math/SafeMath.sol",
      "solcConfig": {
        "version": "0.6.12",
        "settings": {
          "optimizer": {
            "enabled": true,
            "runs": 200
          },
          "outputSelection": {
            "*": {
              "*": [
                "abi",
                "evm.bytecode",
                "evm.deployedBytecode",
                "evm.methodIdentifiers"
              ],
              "": [
                "ast"
              ]
            }
          }
        }
      },
      "imports": [],
      "versionPragmas": [
        "^0.6.0"
      ],
      "artifacts": [
        "SafeMath"
      ]
    },
    "/home/hskang9/standard-protocol/node_modules/@openzeppelin/contracts/token/ERC20/IERC20.sol": {
      "lastModificationDate": 1609182753639,
      "contentHash": "95e76adf687e1a31a4b8ece4e9bb757a",
      "sourceName": "@openzeppelin/contracts/token/ERC20/IERC20.sol",
      "solcConfig": {
        "version": "0.6.12",
        "settings": {
          "optimizer": {
            "enabled": true,
            "runs": 200
          },
          "outputSelection": {
            "*": {
              "*": [
                "abi",
                "evm.bytecode",
                "evm.deployedBytecode",
                "evm.methodIdentifiers"
              ],
              "": [
                "ast"
              ]
            }
          }
        }
      },
      "imports": [],
      "versionPragmas": [
        "^0.6.0"
      ],
      "artifacts": [
        "IERC20"
      ]
    },
    "/home/hskang9/standard-protocol/node_modules/@openzeppelin/contracts/token/ERC20/SafeERC20.sol": {
      "lastModificationDate": 1609182753639,
      "contentHash": "9ad439345c515e1367ef104675b36e7b",
      "sourceName": "@openzeppelin/contracts/token/ERC20/SafeERC20.sol",
      "solcConfig": {
        "version": "0.6.12",
        "settings": {
          "optimizer": {
            "enabled": true,
            "runs": 200
          },
          "outputSelection": {
            "*": {
              "*": [
                "abi",
                "evm.bytecode",
                "evm.deployedBytecode",
                "evm.methodIdentifiers"
              ],
              "": [
                "ast"
              ]
            }
          }
        }
      },
      "imports": [
        "./IERC20.sol",
        "../../math/SafeMath.sol",
        "../../utils/Address.sol"
      ],
      "versionPragmas": [
        "^0.6.0"
      ],
      "artifacts": [
        "SafeERC20"
      ]
    },
    "/home/hskang9/standard-protocol/node_modules/@openzeppelin/contracts/utils/ReentrancyGuard.sol": {
      "lastModificationDate": 1609182752079,
      "contentHash": "d7295fcfe1e67e8b5e0099bdba192e19",
      "sourceName": "@openzeppelin/contracts/utils/ReentrancyGuard.sol",
      "solcConfig": {
        "version": "0.6.12",
        "settings": {
          "optimizer": {
            "enabled": true,
            "runs": 200
          },
          "outputSelection": {
            "*": {
              "*": [
                "abi",
                "evm.bytecode",
                "evm.deployedBytecode",
                "evm.methodIdentifiers"
              ],
              "": [
                "ast"
              ]
            }
          }
        }
      },
      "imports": [],
      "versionPragmas": [
        "^0.6.0"
      ],
      "artifacts": [
        "ReentrancyGuard"
      ]
    },
    "/home/hskang9/standard-protocol/contracts/ownership/Operator.sol": {
      "lastModificationDate": 1609181361062,
      "contentHash": "b27e7aea6ca5bd68b47e2e782130be26",
      "sourceName": "contracts/ownership/Operator.sol",
      "solcConfig": {
        "version": "0.6.12",
        "settings": {
          "optimizer": {
            "enabled": true,
            "runs": 200
          },
          "outputSelection": {
            "*": {
              "*": [
                "abi",
                "evm.bytecode",
                "evm.deployedBytecode",
                "evm.methodIdentifiers"
              ],
              "": [
                "ast"
              ]
            }
          }
        }
      },
      "imports": [
        "@openzeppelin/contracts/GSN/Context.sol",
        "@openzeppelin/contracts/access/Ownable.sol"
      ],
      "versionPragmas": [
        "^0.6.0"
      ],
      "artifacts": [
        "Operator"
      ]
    },
    "/home/hskang9/standard-protocol/contracts/utils/ContractGuard.sol": {
      "lastModificationDate": 1609612106574,
      "contentHash": "4f4fa7a9fda15d428be6e20faf5f2342",
      "sourceName": "contracts/utils/ContractGuard.sol",
      "solcConfig": {
        "version": "0.6.12",
        "settings": {
          "optimizer": {
            "enabled": true,
            "runs": 200
          },
          "outputSelection": {
            "*": {
              "*": [
                "abi",
                "evm.bytecode",
                "evm.deployedBytecode",
                "evm.methodIdentifiers"
              ],
              "": [
                "ast"
              ]
            }
          }
        }
      },
      "imports": [],
      "versionPragmas": [
        "^0.6.12"
      ],
      "artifacts": [
        "ContractGuard"
      ]
    },
    "/home/hskang9/standard-protocol/node_modules/@openzeppelin/contracts/utils/Address.sol": {
      "lastModificationDate": 1609182752075,
      "contentHash": "6b0498e1feb1d70edaf0ee5546e07a46",
      "sourceName": "@openzeppelin/contracts/utils/Address.sol",
      "solcConfig": {
        "version": "0.6.12",
        "settings": {
          "optimizer": {
            "enabled": true,
            "runs": 200
          },
          "outputSelection": {
            "*": {
              "*": [
                "abi",
                "evm.bytecode",
                "evm.deployedBytecode",
                "evm.methodIdentifiers"
              ],
              "": [
                "ast"
              ]
            }
          }
        }
      },
      "imports": [],
      "versionPragmas": [
        "^0.6.2"
      ],
      "artifacts": [
        "Address"
      ]
    },
    "/home/hskang9/standard-protocol/node_modules/@openzeppelin/contracts/GSN/Context.sol": {
      "lastModificationDate": 1609182752075,
      "contentHash": "af1b36323856d0d1550abc7f878a8208",
      "sourceName": "@openzeppelin/contracts/GSN/Context.sol",
      "solcConfig": {
        "version": "0.6.12",
        "settings": {
          "optimizer": {
            "enabled": true,
            "runs": 200
          },
          "outputSelection": {
            "*": {
              "*": [
                "abi",
                "evm.bytecode",
                "evm.deployedBytecode",
                "evm.methodIdentifiers"
              ],
              "": [
                "ast"
              ]
            }
          }
        }
      },
      "imports": [],
      "versionPragmas": [
        "^0.6.0"
      ],
      "artifacts": [
        "Context"
      ]
    },
    "/home/hskang9/standard-protocol/node_modules/@openzeppelin/contracts/access/Ownable.sol": {
      "lastModificationDate": 1609182752075,
      "contentHash": "140e80ebd07ed05e7fe907c531e6746f",
      "sourceName": "@openzeppelin/contracts/access/Ownable.sol",
      "solcConfig": {
        "version": "0.6.12",
        "settings": {
          "optimizer": {
            "enabled": true,
            "runs": 200
          },
          "outputSelection": {
            "*": {
              "*": [
                "abi",
                "evm.bytecode",
                "evm.deployedBytecode",
                "evm.methodIdentifiers"
              ],
              "": [
                "ast"
              ]
            }
          }
        }
      },
      "imports": [
        "../GSN/Context.sol"
      ],
      "versionPragmas": [
        "^0.6.0"
      ],
      "artifacts": [
        "Ownable"
      ]
    },
    "/home/hskang9/standard-protocol/contracts/utils/Epoch.sol": {
      "lastModificationDate": 1609612029026,
      "contentHash": "0e5f0c5b7b804380f7074cc5006dd865",
      "sourceName": "contracts/utils/Epoch.sol",
      "solcConfig": {
        "version": "0.6.12",
        "settings": {
          "optimizer": {
            "enabled": true,
            "runs": 200
          },
          "outputSelection": {
            "*": {
              "*": [
                "abi",
                "evm.bytecode",
                "evm.deployedBytecode",
                "evm.methodIdentifiers"
              ],
              "": [
                "ast"
              ]
            }
          }
        }
      },
      "imports": [
        "@openzeppelin/contracts/math/SafeMath.sol",
        "../ownership/Operator.sol"
      ],
      "versionPragmas": [
        "^0.6.0"
      ],
      "artifacts": [
        "Epoch"
      ]
    },
    "/home/hskang9/standard-protocol/node_modules/@openzeppelin/contracts/token/ERC20/ERC20.sol": {
      "lastModificationDate": 1609182753635,
      "contentHash": "620e59a5f2a9fe517c47500d5a27af91",
      "sourceName": "@openzeppelin/contracts/token/ERC20/ERC20.sol",
      "solcConfig": {
        "version": "0.6.12",
        "settings": {
          "optimizer": {
            "enabled": true,
            "runs": 200
          },
          "outputSelection": {
            "*": {
              "*": [
                "abi",
                "evm.bytecode",
                "evm.deployedBytecode",
                "evm.methodIdentifiers"
              ],
              "": [
                "ast"
              ]
            }
          }
        }
      },
      "imports": [
        "../../GSN/Context.sol",
        "./IERC20.sol",
        "../../math/SafeMath.sol",
        "../../utils/Address.sol"
      ],
      "versionPragmas": [
        "^0.6.0"
      ],
      "artifacts": [
        "ERC20"
      ]
    },
    "/home/hskang9/standard-protocol/contracts/treasury/ReserveBank.sol": {
      "lastModificationDate": 1609611776745,
      "contentHash": "07c8b4ebef88558e24bdd4d5ffd8eac5",
      "sourceName": "contracts/treasury/ReserveBank.sol",
      "solcConfig": {
        "version": "0.6.12",
        "settings": {
          "optimizer": {
            "enabled": true,
            "runs": 200
          },
          "outputSelection": {
            "*": {
              "*": [
                "abi",
                "evm.bytecode",
                "evm.deployedBytecode",
                "evm.methodIdentifiers"
              ],
              "": [
                "ast"
              ]
            }
          }
        }
      },
      "imports": [
        "@openzeppelin/contracts/math/Math.sol",
        "@openzeppelin/contracts/token/ERC20/IERC20.sol",
        "@openzeppelin/contracts/token/ERC20/SafeERC20.sol",
        "@openzeppelin/contracts/utils/ReentrancyGuard.sol"
      ],
      "versionPragmas": [
        "^0.6.0"
      ],
      "artifacts": []
    },
    "/home/hskang9/standard-protocol/contracts/pool/LPTokenWrapper.sol": {
      "lastModificationDate": 1609182270462,
      "contentHash": "d7097c700030523d708ccae708277331",
      "sourceName": "contracts/pool/LPTokenWrapper.sol",
      "solcConfig": {
        "version": "0.6.12",
        "settings": {
          "optimizer": {
            "enabled": true,
            "runs": 200
          },
          "outputSelection": {
            "*": {
              "*": [
                "abi",
                "evm.bytecode",
                "evm.deployedBytecode",
                "evm.methodIdentifiers"
              ],
              "": [
                "ast"
              ]
            }
          }
        }
      },
      "imports": [
        "@openzeppelin/contracts/math/SafeMath.sol",
        "@openzeppelin/contracts/token/ERC20/SafeERC20.sol",
        "@openzeppelin/contracts/token/ERC20/IERC20.sol"
      ],
      "versionPragmas": [
        "^0.6.0"
      ],
      "artifacts": [
        "LPTokenWrapper"
      ]
    },
    "/home/hskang9/standard-protocol/contracts/pool/LPRewardPool.sol": {
      "lastModificationDate": 1609309589157,
      "contentHash": "ba436baf2b107c7235ad65e7277f8f29",
      "sourceName": "contracts/pool/LPRewardPool.sol",
      "solcConfig": {
        "version": "0.6.12",
        "settings": {
          "optimizer": {
            "enabled": true,
            "runs": 200
          },
          "outputSelection": {
            "*": {
              "*": [
                "abi",
                "evm.bytecode",
                "evm.deployedBytecode",
                "evm.methodIdentifiers"
              ],
              "": [
                "ast"
              ]
            }
          }
        }
      },
      "imports": [
        "@openzeppelin/contracts/math/Math.sol",
        "@openzeppelin/contracts/math/SafeMath.sol",
        "@openzeppelin/contracts/token/ERC20/IERC20.sol",
        "@openzeppelin/contracts/utils/Address.sol",
        "@openzeppelin/contracts/token/ERC20/SafeERC20.sol",
        "../interfaces/IRewardDistributionRecipient.sol",
        "./LPTokenWrapper.sol"
      ],
      "versionPragmas": [
        "^0.6.0"
      ],
      "artifacts": [
        "DAIBACLPTokenSharePool"
      ]
    },
    "/home/hskang9/standard-protocol/contracts/interfaces/IRewardDistributionRecipient.sol": {
      "lastModificationDate": 1609182369704,
      "contentHash": "6613b0726e0427834b12fcad0f08b6b5",
      "sourceName": "contracts/interfaces/IRewardDistributionRecipient.sol",
      "solcConfig": {
        "version": "0.6.12",
        "settings": {
          "optimizer": {
            "enabled": true,
            "runs": 200
          },
          "outputSelection": {
            "*": {
              "*": [
                "abi",
                "evm.bytecode",
                "evm.deployedBytecode",
                "evm.methodIdentifiers"
              ],
              "": [
                "ast"
              ]
            }
          }
        }
      },
      "imports": [
        "@openzeppelin/contracts/access/Ownable.sol"
      ],
      "versionPragmas": [
        "^0.6.0"
      ],
      "artifacts": [
        "IRewardDistributionRecipient"
      ]
    },
    "/home/hskang9/standard-protocol/node_modules/@openzeppelin/contracts/token/ERC20/ERC20Burnable.sol": {
      "lastModificationDate": 1609182753635,
      "contentHash": "e7d9974ca7596843e7515c1b27a2d0a8",
      "sourceName": "@openzeppelin/contracts/token/ERC20/ERC20Burnable.sol",
      "solcConfig": {
        "version": "0.6.12",
        "settings": {
          "optimizer": {
            "enabled": true,
            "runs": 200
          },
          "outputSelection": {
            "*": {
              "*": [
                "abi",
                "evm.bytecode",
                "evm.deployedBytecode",
                "evm.methodIdentifiers"
              ],
              "": [
                "ast"
              ]
            }
          }
        }
      },
      "imports": [
        "../../GSN/Context.sol",
        "./ERC20.sol"
      ],
      "versionPragmas": [
        "^0.6.0"
      ],
      "artifacts": [
        "ERC20Burnable"
      ]
    },
    "/home/hskang9/standard-protocol/contracts/token/Standard.sol": {
      "lastModificationDate": 1609325425736,
      "contentHash": "e0fe572a58eda43e6770d9ceeb4f80b4",
      "sourceName": "contracts/token/Standard.sol",
      "solcConfig": {
        "version": "0.6.12",
        "settings": {
          "optimizer": {
            "enabled": true,
            "runs": 200
          },
          "outputSelection": {
            "*": {
              "*": [
                "abi",
                "evm.bytecode",
                "evm.deployedBytecode",
                "evm.methodIdentifiers"
              ],
              "": [
                "ast"
              ]
            }
          }
        }
      },
      "imports": [
        "@openzeppelin/contracts/token/ERC20/ERC20Burnable.sol",
        "../ownership/Operator.sol"
      ],
      "versionPragmas": [
        "^0.6.0"
      ],
      "artifacts": [
        "Cash"
      ]
    },
    "/home/hskang9/standard-protocol/contracts/token/Cash.sol": {
      "lastModificationDate": 1609182794359,
      "contentHash": "caec39c1e347ea5b4857a0cfd0f53928",
      "sourceName": "contracts/token/Cash.sol",
      "solcConfig": {
        "version": "0.6.12",
        "settings": {
          "optimizer": {
            "enabled": true,
            "runs": 200
          },
          "outputSelection": {
            "*": {
              "*": [
                "abi",
                "evm.bytecode",
                "evm.deployedBytecode",
                "evm.methodIdentifiers"
              ],
              "": [
                "ast"
              ]
            }
          }
        }
      },
      "imports": [
        "@openzeppelin/contracts/token/ERC20/ERC20Burnable.sol",
        "../ownership/Operator.sol"
      ],
      "versionPragmas": [
        "^0.6.0"
      ],
      "artifacts": [
        "Cash"
      ]
    },
    "/home/hskang9/standard-protocol/contracts/token/Block.sol": {
      "lastModificationDate": 1609325406804,
      "contentHash": "33ae691bfdccfeb16d3a5dd2e18c22ae",
      "sourceName": "contracts/token/Block.sol",
      "solcConfig": {
        "version": "0.6.12",
        "settings": {
          "optimizer": {
            "enabled": true,
            "runs": 200
          },
          "outputSelection": {
            "*": {
              "*": [
                "abi",
                "evm.bytecode",
                "evm.deployedBytecode",
                "evm.methodIdentifiers"
              ],
              "": [
                "ast"
              ]
            }
          }
        }
      },
      "imports": [
        "@openzeppelin/contracts/token/ERC20/ERC20Burnable.sol",
        "../ownership/Operator.sol"
      ],
      "versionPragmas": [
        "^0.6.0"
      ],
      "artifacts": [
        "Cash"
      ]
    },
    "/home/hskang9/standard-protocol/contracts/lib/UniswapV2Library.sol": {
      "lastModificationDate": 1609181525972,
      "contentHash": "f85400885f1814f2cc307c5026b9e7d1",
      "sourceName": "contracts/lib/UniswapV2Library.sol",
      "solcConfig": {
        "version": "0.6.12",
        "settings": {
          "optimizer": {
            "enabled": true,
            "runs": 200
          },
          "outputSelection": {
            "*": {
              "*": [
                "abi",
                "evm.bytecode",
                "evm.deployedBytecode",
                "evm.methodIdentifiers"
              ],
              "": [
                "ast"
              ]
            }
          }
        }
      },
      "imports": [
        "@openzeppelin/contracts/math/SafeMath.sol",
        "../interfaces/IUniswapV2Pair.sol"
      ],
      "versionPragmas": [
        "^0.6.0"
      ],
      "artifacts": [
        "UniswapV2Library"
      ]
    },
    "/home/hskang9/standard-protocol/contracts/interfaces/IUniswapV2Pair.sol": {
      "lastModificationDate": 1609181684791,
      "contentHash": "cad26b3ca62b5da7f988108674759fcf",
      "sourceName": "contracts/interfaces/IUniswapV2Pair.sol",
      "solcConfig": {
        "version": "0.6.12",
        "settings": {
          "optimizer": {
            "enabled": true,
            "runs": 200
          },
          "outputSelection": {
            "*": {
              "*": [
                "abi",
                "evm.bytecode",
                "evm.deployedBytecode",
                "evm.methodIdentifiers"
              ],
              "": [
                "ast"
              ]
            }
          }
        }
      },
      "imports": [],
      "versionPragmas": [
        "^0.6.0"
      ],
      "artifacts": [
        "IUniswapV2Pair"
      ]
    },
    "/home/hskang9/standard-protocol/contracts/lib/UniswapV2OracleLibrary.sol": {
      "lastModificationDate": 1609181525972,
      "contentHash": "4801ad9fc6df6d1a79a3550e367f46d7",
      "sourceName": "contracts/lib/UniswapV2OracleLibrary.sol",
      "solcConfig": {
        "version": "0.6.12",
        "settings": {
          "optimizer": {
            "enabled": true,
            "runs": 200
          },
          "outputSelection": {
            "*": {
              "*": [
                "abi",
                "evm.bytecode",
                "evm.deployedBytecode",
                "evm.methodIdentifiers"
              ],
              "": [
                "ast"
              ]
            }
          }
        }
      },
      "imports": [
        "./FixedPoint.sol",
        "../interfaces/IUniswapV2Pair.sol"
      ],
      "versionPragmas": [
        "^0.6.0"
      ],
      "artifacts": [
        "UniswapV2OracleLibrary"
      ]
    },
    "/home/hskang9/standard-protocol/contracts/lib/FixedPoint.sol": {
      "lastModificationDate": 1609181525972,
      "contentHash": "00056f26f21a66f34072cfb83e014859",
      "sourceName": "contracts/lib/FixedPoint.sol",
      "solcConfig": {
        "version": "0.6.12",
        "settings": {
          "optimizer": {
            "enabled": true,
            "runs": 200
          },
          "outputSelection": {
            "*": {
              "*": [
                "abi",
                "evm.bytecode",
                "evm.deployedBytecode",
                "evm.methodIdentifiers"
              ],
              "": [
                "ast"
              ]
            }
          }
        }
      },
      "imports": [
        "./Babylonian.sol"
      ],
      "versionPragmas": [
        "^0.6.0"
      ],
      "artifacts": [
        "FixedPoint"
      ]
    },
    "/home/hskang9/standard-protocol/contracts/lib/Babylonian.sol": {
      "lastModificationDate": 1609181525972,
      "contentHash": "d5ea6bbf56e2af70dcfccd6ac6100339",
      "sourceName": "contracts/lib/Babylonian.sol",
      "solcConfig": {
        "version": "0.6.12",
        "settings": {
          "optimizer": {
            "enabled": true,
            "runs": 200
          },
          "outputSelection": {
            "*": {
              "*": [
                "abi",
                "evm.bytecode",
                "evm.deployedBytecode",
                "evm.methodIdentifiers"
              ],
              "": [
                "ast"
              ]
            }
          }
        }
      },
      "imports": [],
      "versionPragmas": [
        "^0.6.0"
      ],
      "artifacts": [
        "Babylonian"
      ]
    },
    "/home/hskang9/standard-protocol/contracts/oracle/PriceConsumerV3.sol": {
      "lastModificationDate": 1609690820419,
      "contentHash": "3f0e2c942d770a3716986f276011d960",
      "sourceName": "contracts/oracle/PriceConsumerV3.sol",
      "solcConfig": {
        "version": "0.6.12",
        "settings": {
          "optimizer": {
            "enabled": true,
            "runs": 200
          },
          "outputSelection": {
            "*": {
              "*": [
                "abi",
                "evm.bytecode",
                "evm.deployedBytecode",
                "evm.methodIdentifiers"
              ],
              "": [
                "ast"
              ]
            }
          }
        }
      },
      "imports": [
        "./AggregatorV3Interface.sol",
        "../ownership/Operator.sol"
      ],
      "versionPragmas": [
        "^0.6.7"
      ],
      "artifacts": [
        "PriceConsumerV3"
      ]
    },
    "/home/hskang9/standard-protocol/contracts/oracle/AggregatorV3Interface.sol": {
      "lastModificationDate": 1609687672389,
      "contentHash": "8e23314b120377fd91b8dca3a69acbf1",
      "sourceName": "contracts/oracle/AggregatorV3Interface.sol",
      "solcConfig": {
        "version": "0.6.12",
        "settings": {
          "optimizer": {
            "enabled": true,
            "runs": 200
          },
          "outputSelection": {
            "*": {
              "*": [
                "abi",
                "evm.bytecode",
                "evm.deployedBytecode",
                "evm.methodIdentifiers"
              ],
              "": [
                "ast"
              ]
            }
          }
        }
      },
      "imports": [],
      "versionPragmas": [
        ">=0.6.0"
      ],
      "artifacts": [
        "AggregatorV3Interface"
      ]
    },
    "/home/hskang9/standard-protocol/contracts/interfaces/IDistributor.sol": {
      "lastModificationDate": 1609181684787,
      "contentHash": "fcd426ede4089c194f32c368788169ac",
      "sourceName": "contracts/interfaces/IDistributor.sol",
      "solcConfig": {
        "version": "0.6.12",
        "settings": {
          "optimizer": {
            "enabled": true,
            "runs": 200
          },
          "outputSelection": {
            "*": {
              "*": [
                "abi",
                "evm.bytecode",
                "evm.deployedBytecode",
                "evm.methodIdentifiers"
              ],
              "": [
                "ast"
              ]
            }
          }
        }
      },
      "imports": [],
      "versionPragmas": [
        "^0.6.0"
      ],
      "artifacts": [
        "IDistributor"
      ]
    },
    "/home/hskang9/standard-protocol/contracts/interfaces/IOracle.sol": {
      "lastModificationDate": 1609181684787,
      "contentHash": "ad080193b29ff76168e8a5a3ac9659a2",
      "sourceName": "contracts/interfaces/IOracle.sol",
      "solcConfig": {
        "version": "0.6.12",
        "settings": {
          "optimizer": {
            "enabled": true,
            "runs": 200
          },
          "outputSelection": {
            "*": {
              "*": [
                "abi",
                "evm.bytecode",
                "evm.deployedBytecode",
                "evm.methodIdentifiers"
              ],
              "": [
                "ast"
              ]
            }
          }
        }
      },
      "imports": [],
      "versionPragmas": [
        "^0.6.0"
      ],
      "artifacts": [
        "IOracle"
      ]
    },
    "/home/hskang9/standard-protocol/contracts/interfaces/ISimpleERCFund.sol": {
      "lastModificationDate": 1609181684791,
      "contentHash": "dc32c1cd6cbfd13811e112b523a1bfb4",
      "sourceName": "contracts/interfaces/ISimpleERCFund.sol",
      "solcConfig": {
        "version": "0.6.12",
        "settings": {
          "optimizer": {
            "enabled": true,
            "runs": 200
          },
          "outputSelection": {
            "*": {
              "*": [
                "abi",
                "evm.bytecode",
                "evm.deployedBytecode",
                "evm.methodIdentifiers"
              ],
              "": [
                "ast"
              ]
            }
          }
        }
      },
      "imports": [],
      "versionPragmas": [
        "^0.6.0"
      ],
      "artifacts": [
        "ISimpleERCFund"
      ]
    },
    "/home/hskang9/standard-protocol/contracts/interfaces/IUniswapV2Callee.sol": {
      "lastModificationDate": 1609181684791,
      "contentHash": "5e6e1c54ac957e611e3e0202b1c45dfb",
      "sourceName": "contracts/interfaces/IUniswapV2Callee.sol",
      "solcConfig": {
        "version": "0.6.12",
        "settings": {
          "optimizer": {
            "enabled": true,
            "runs": 200
          },
          "outputSelection": {
            "*": {
              "*": [
                "abi",
                "evm.bytecode",
                "evm.deployedBytecode",
                "evm.methodIdentifiers"
              ],
              "": [
                "ast"
              ]
            }
          }
        }
      },
      "imports": [],
      "versionPragmas": [
        "^0.6.0"
      ],
      "artifacts": [
        "IUniswapV2Callee"
      ]
    },
    "/home/hskang9/standard-protocol/contracts/interfaces/IUniswapV2ERC20.sol": {
      "lastModificationDate": 1609181684791,
      "contentHash": "b8783f54e4d3c7420b2a77f5ba51cdc9",
      "sourceName": "contracts/interfaces/IUniswapV2ERC20.sol",
      "solcConfig": {
        "version": "0.6.12",
        "settings": {
          "optimizer": {
            "enabled": true,
            "runs": 200
          },
          "outputSelection": {
            "*": {
              "*": [
                "abi",
                "evm.bytecode",
                "evm.deployedBytecode",
                "evm.methodIdentifiers"
              ],
              "": [
                "ast"
              ]
            }
          }
        }
      },
      "imports": [],
      "versionPragmas": [
        "^0.6.0"
      ],
      "artifacts": [
        "IUniswapV2ERC20"
      ]
    },
    "/home/hskang9/standard-protocol/contracts/interfaces/IUniswapV2Factory.sol": {
      "lastModificationDate": 1609181684791,
      "contentHash": "5dc90cb59bad934109d2d62b9fa34d1d",
      "sourceName": "contracts/interfaces/IUniswapV2Factory.sol",
      "solcConfig": {
        "version": "0.6.12",
        "settings": {
          "optimizer": {
            "enabled": true,
            "runs": 200
          },
          "outputSelection": {
            "*": {
              "*": [
                "abi",
                "evm.bytecode",
                "evm.deployedBytecode",
                "evm.methodIdentifiers"
              ],
              "": [
                "ast"
              ]
            }
          }
        }
      },
      "imports": [],
      "versionPragmas": [
        "^0.6.0"
      ],
      "artifacts": [
        "IUniswapV2Factory"
      ]
    },
    "/home/hskang9/standard-protocol/contracts/lib/Safe112.sol": {
      "lastModificationDate": 1609181525972,
      "contentHash": "c1f8fe293f6029662391cef012a0eeef",
      "sourceName": "contracts/lib/Safe112.sol",
      "solcConfig": {
        "version": "0.6.12",
        "settings": {
          "optimizer": {
            "enabled": true,
            "runs": 200
          },
          "outputSelection": {
            "*": {
              "*": [
                "abi",
                "evm.bytecode",
                "evm.deployedBytecode",
                "evm.methodIdentifiers"
              ],
              "": [
                "ast"
              ]
            }
          }
        }
      },
      "imports": [],
      "versionPragmas": [
        "^0.6.0"
      ],
      "artifacts": [
        "Safe112"
      ]
    },
    "/home/hskang9/standard-protocol/contracts/Migrations.sol": {
      "lastModificationDate": 1609181193611,
      "contentHash": "50b3b1dc92806dc8f604fc8c5c65518f",
      "sourceName": "contracts/Migrations.sol",
      "solcConfig": {
        "version": "0.6.12",
        "settings": {
          "optimizer": {
            "enabled": true,
            "runs": 200
          },
          "outputSelection": {
            "*": {
              "*": [
                "abi",
                "evm.bytecode",
                "evm.deployedBytecode",
                "evm.methodIdentifiers"
              ],
              "": [
                "ast"
              ]
            }
          }
        }
      },
      "imports": [],
      "versionPragmas": [
        ">=0.4.22 <0.9.0"
      ],
      "artifacts": [
        "Migrations"
      ]
    },
    "/home/hskang9/standard-protocol/contracts/treasury/BlockMarket.sol": {
      "lastModificationDate": 1609325477352,
      "contentHash": "d41d8cd98f00b204e9800998ecf8427e",
      "sourceName": "contracts/treasury/BlockMarket.sol",
      "solcConfig": {
        "version": "0.6.12",
        "settings": {
          "optimizer": {
            "enabled": true,
            "runs": 200
          },
          "outputSelection": {
            "*": {
              "*": [
                "abi",
                "evm.bytecode",
                "evm.deployedBytecode",
                "evm.methodIdentifiers"
              ],
              "": [
                "ast"
              ]
            }
          }
        }
      },
      "imports": [],
      "versionPragmas": [],
      "artifacts": []
    },
    "/home/hskang9/standard-protocol/contracts/treasury/SeignioragePool.sol": {
      "lastModificationDate": 1609325467056,
      "contentHash": "d41d8cd98f00b204e9800998ecf8427e",
      "sourceName": "contracts/treasury/SeignioragePool.sol",
      "solcConfig": {
        "version": "0.6.12",
        "settings": {
          "optimizer": {
            "enabled": true,
            "runs": 200
          },
          "outputSelection": {
            "*": {
              "*": [
                "abi",
                "evm.bytecode",
                "evm.deployedBytecode",
                "evm.methodIdentifiers"
              ],
              "": [
                "ast"
              ]
            }
          }
        }
      },
      "imports": [],
      "versionPragmas": [],
      "artifacts": []
    }
  }
}
